odoo/addons/project_internal_access_from_portal/README.rst
odoo/addons/project_internal_access_from_portal/__init__.py
odoo/addons/project_internal_access_from_portal/__manifest__.py
odoo/addons/project_internal_access_from_portal/demo/demo_data.xml
odoo/addons/project_internal_access_from_portal/i18n/it.po
odoo/addons/project_internal_access_from_portal/i18n/project_internal_access_from_portal.pot
odoo/addons/project_internal_access_from_portal/models/__init__.py
odoo/addons/project_internal_access_from_portal/models/project_project.py
odoo/addons/project_internal_access_from_portal/readme/CONFIGURE.md
odoo/addons/project_internal_access_from_portal/readme/CONTEXT.md
odoo/addons/project_internal_access_from_portal/readme/CONTRIBUTORS.md
odoo/addons/project_internal_access_from_portal/readme/DESCRIPTION.md
odoo/addons/project_internal_access_from_portal/readme/USAGE.md
odoo/addons/project_internal_access_from_portal/security/portal_project_rules.xml
odoo/addons/project_internal_access_from_portal/static/description/icon.png
odoo/addons/project_internal_access_from_portal/static/description/index.html
odoo/addons/project_internal_access_from_portal/tests/__init__.py
odoo/addons/project_internal_access_from_portal/tests/test_portal_internal_access.py
odoo_addon_project_internal_access_from_portal-16.0.1.0.1.dist-info/METADATA
odoo_addon_project_internal_access_from_portal-16.0.1.0.1.dist-info/WHEEL
odoo_addon_project_internal_access_from_portal-16.0.1.0.1.dist-info/top_level.txt
odoo_addon_project_internal_access_from_portal-16.0.1.0.1.dist-info/RECORD
